libsrd/__init__.py
libsrd/__version__.py
libsrd/htmlbuilder.py
libsrd/image_convert.py
libsrd/markhtml.py
libsrd/merge_pdf.py
libsrd/pdf_resizer.py
libsrd/table.py
libsrd-1.3.2.dist-info/licenses/LICENSE
libsrd-1.3.2.dist-info/METADATA
libsrd-1.3.2.dist-info/WHEEL
libsrd-1.3.2.dist-info/entry_points.txt
libsrd-1.3.2.dist-info/top_level.txt
libsrd-1.3.2.dist-info/RECORD
