Metadata-Version: 2.4
Name: libsrd
Version: 1.3.2
Summary: LibSrd is a library containing my modules I use repeatedly.
Home-page: https://github.com/Samdavis112/libsrd
Author: Sam Davis
Author-email: srd076@icloud.com
License-File: LICENSE
Requires-Dist: pillow
Requires-Dist: tabulate
Requires-Dist: pypdf
Dynamic: author
Dynamic: author-email
Dynamic: description
Dynamic: home-page
Dynamic: license-file
Dynamic: requires-dist
Dynamic: summary
